ItClust/DEC.py
ItClust/ItClust.py
ItClust/SAE.py
ItClust/__init__.py
ItClust/preprocessing.py
ItClust-1.2.0.dist-info/DESCRIPTION.rst
ItClust-1.2.0.dist-info/METADATA
ItClust-1.2.0.dist-info/RECORD
ItClust-1.2.0.dist-info/WHEEL
ItClust-1.2.0.dist-info/metadata.json
ItClust-1.2.0.dist-info/top_level.txt
