Metadata-Version: 2.0
Name: ItClust
Version: 1.2.0
Summary: An Iterative Transfer learning algorithm for scRNA-seq Clustering
Home-page: https://github.com/jianhuupenn/ItClust
Author: Jian Hu
Author-email: jianhu@pennmedicine.upenn.edu
License: UNKNOWN
Platform: UNKNOWN
Classifier: Programming Language :: Python :: 3
Classifier: License :: OSI Approved :: MIT License
Classifier: Operating System :: OS Independent
Requires-Python: >=3.6
Requires-Dist: anndata
Requires-Dist: keras
Requires-Dist: natsort
Requires-Dist: numpy
Requires-Dist: pandas
Requires-Dist: scanpy
Requires-Dist: scipy
Requires-Dist: sklearn
